setup.py
nscms/__init__.py
nscms/forms.py
nscms/models.py
nscms.egg-info/PKG-INFO
nscms.egg-info/SOURCES.txt
nscms.egg-info/dependency_links.txt
nscms.egg-info/requires.txt
nscms.egg-info/top_level.txt
nscms/base/__init__.py
nscms/base/content/__init__.py
nscms/base/content/models.py
nscms/base/simplenews/__init__.py
nscms/base/simplenews/models.py
nscms/base/simplepage/__init__.py
nscms/base/simplepage/models.py
nscms/contrib/__init__.py
nscms/contrib/banner/__init__.py
nscms/contrib/banner/admin.py
nscms/contrib/banner/models.py
nscms/contrib/banner/locale/pt_BR/LC_MESSAGES/django.mo
nscms/contrib/banner/locale/pt_BR/LC_MESSAGES/django.po
nscms/contrib/banner/migrations/0001_initial.py
nscms/contrib/banner/migrations/__init__.py
nscms/contrib/basicnews/__init__.py
nscms/contrib/basicnews/admin.py
nscms/contrib/basicnews/models.py
nscms/contrib/basicnews/tests.py
nscms/contrib/basicnews/views.py
nscms/contrib/basicnews/migrations/0001_initial.py
nscms/contrib/basicnews/migrations/__init__.py
nscms/contrib/block/__init__.py
nscms/contrib/block/admin.py
nscms/contrib/block/forms.py
nscms/contrib/block/models.py
nscms/contrib/block/locale/pt_BR/LC_MESSAGES/django.mo
nscms/contrib/block/locale/pt_BR/LC_MESSAGES/django.po
nscms/contrib/block/migrations/0001_initial.py
nscms/contrib/block/migrations/0002_auto__add_field_block_is_template__add_index_block_created__add_index_.py
nscms/contrib/block/migrations/__init__.py
nscms/contrib/block/templatetags/__init__.py
nscms/contrib/block/templatetags/nscms_block.py
nscms/contrib/newsletter/__init__.py
nscms/contrib/newsletter/models.py
nscms/contrib/newsletter/tests.py
nscms/contrib/newsletter/urls.py
nscms/contrib/newsletter/views.py
nscms/db/__init__.py
nscms/db/models/__init__.py
nscms/db/models/youtube.py
nscms/helpers/__init__.py
nscms/helpers/upload.py
nscms/helpers/userprofile/__init__.py
nscms/helpers/userprofile/models.py
nscms/helpers/userprofile/tests.py
nscms/helpers/userprofile/views.py
nscms/locale/pt_BR/LC_MESSAGES/django.mo
nscms/locale/pt_BR/LC_MESSAGES/django.po
nscms/localflavor/__init__.py
nscms/localflavor/br/__init__.py
